Metadata-Version: 1.0
Name: oop-probability
Version: 0.1
Summary: Gaussian and Binomial distributions
Home-page: UNKNOWN
Author: Amani Ezzat
Author-email: amanyezat@gmail.com
License: UNKNOWN
Platform: UNKNOWN
